dynamixel_async/__init__.py
dynamixel_async/constants.py
dynamixel_async/controller.py
dynamixel_async/exceptions.py
dynamixel_async/protocol.py
dynamixel_async/servo.py
dynamixel_async/models/__init__.py
dynamixel_async/models/base.py
dynamixel_async/models/xm430.py
dynamixel_async-0.2.0.dist-info/METADATA
dynamixel_async-0.2.0.dist-info/WHEEL
dynamixel_async-0.2.0.dist-info/licenses/LICENSE
dynamixel_async-0.2.0.dist-info/RECORD
