Metadata-Version: 2.4
Name: dynamixel-async
Version: 0.2.0
Summary: High-level Python library for Dynamixel servos with async support and comprehensive control table definitions
Author-email: Jae Won Yong <yongjaewon@gmail.com>
License: MIT License
License-File: LICENSE
Keywords: async,control,dynamixel,motor,robotics,servo,xm430
Classifier: Development Status :: 4 - Beta
Classifier: Intended Audience :: Developers
Classifier: License :: OSI Approved :: MIT License
Classifier: Operating System :: OS Independent
Classifier: Programming Language :: Python :: 3
Classifier: Programming Language :: Python :: 3.7
Classifier: Programming Language :: Python :: 3.8
Classifier: Programming Language :: Python :: 3.9
Classifier: Programming Language :: Python :: 3.10
Classifier: Programming Language :: Python :: 3.11
Classifier: Topic :: Software Development :: Libraries
Classifier: Topic :: Software Development :: Libraries :: Python Modules
Classifier: Topic :: System :: Hardware
Requires-Python: >=3.7
Requires-Dist: dynamixel-sdk>=3.7.0
Requires-Dist: pyserial>=3.5
Provides-Extra: dev
Requires-Dist: black>=22.0.0; extra == 'dev'
Requires-Dist: isort>=5.0.0; extra == 'dev'
Requires-Dist: mypy>=0.900; extra == 'dev'
Requires-Dist: pytest-asyncio>=0.18.0; extra == 'dev'
Requires-Dist: pytest>=7.0.0; extra == 'dev'
